c7n_gcp/__init__.py
c7n_gcp/client.py
c7n_gcp/entry.py
c7n_gcp/handler.py
c7n_gcp/mu.py
c7n_gcp/output.py
c7n_gcp/policy.py
c7n_gcp/provider.py
c7n_gcp/query.py
c7n_gcp/region.py
c7n_gcp/regions.json
c7n_gcp/utils.py
c7n_gcp/actions/__init__.py
c7n_gcp/actions/core.py
c7n_gcp/actions/cscc.py
c7n_gcp/actions/iampolicy.py
c7n_gcp/actions/labels.py
c7n_gcp/actions/notify.py
c7n_gcp/filters/__init__.py
c7n_gcp/filters/alerts.py
c7n_gcp/filters/iampolicy.py
c7n_gcp/filters/labels.py
c7n_gcp/filters/metrics.py
c7n_gcp/filters/recommender.json
c7n_gcp/filters/recommender.py
c7n_gcp/filters/sccfindings.py
c7n_gcp/filters/timerange.py
c7n_gcp/resources/__init__.py
c7n_gcp/resources/appengine.py
c7n_gcp/resources/armor.py
c7n_gcp/resources/artifactregistry.py
c7n_gcp/resources/bigquery.py
c7n_gcp/resources/bigtable.py
c7n_gcp/resources/build.py
c7n_gcp/resources/certificatemanager.py
c7n_gcp/resources/cloudbilling.py
c7n_gcp/resources/cloudrun.py
c7n_gcp/resources/compute.py
c7n_gcp/resources/dataflow.py
c7n_gcp/resources/datafusion.py
c7n_gcp/resources/dataproc.py
c7n_gcp/resources/deploymentmanager.py
c7n_gcp/resources/dns.py
c7n_gcp/resources/function.py
c7n_gcp/resources/gke.py
c7n_gcp/resources/iam.py
c7n_gcp/resources/kms.py
c7n_gcp/resources/loadbalancer.py
c7n_gcp/resources/logging.py
c7n_gcp/resources/memstore.py
c7n_gcp/resources/mlengine.py
c7n_gcp/resources/network.py
c7n_gcp/resources/notebook.py
c7n_gcp/resources/osconfig.py
c7n_gcp/resources/pubsub.py
c7n_gcp/resources/resource_map.py
c7n_gcp/resources/resourcemanager.py
c7n_gcp/resources/secret.py
c7n_gcp/resources/service.py
c7n_gcp/resources/source.py
c7n_gcp/resources/spanner.py
c7n_gcp/resources/sql.py
c7n_gcp/resources/storage.py
c7n_gcp-0.4.48.dist-info/METADATA
c7n_gcp-0.4.48.dist-info/WHEEL
c7n_gcp-0.4.48.dist-info/RECORD
