Metadata-Version: 2.4
Name: c7n_gcp
Version: 0.4.48
Summary: Cloud Custodian - Google Cloud Provider
Project-URL: homepage, https://cloudcustodian.io
Project-URL: repository, https://github.com/cloud-custodian/cloud-custodian
Project-URL: documentation, https://cloudcustodian.io/docs/
Author: Cloud Custodian Project
License-Expression: Apache-2.0
Classifier: License :: OSI Approved :: Apache Software License
Classifier: Topic :: System :: Distributed Computing
Classifier: Topic :: System :: Systems Administration
Requires-Python: <4.0.0,>=3.9.2
Requires-Dist: c7n ==0.9.49
Requires-Dist: google-api-python-client ==2.188.0
Requires-Dist: google-auth ==2.47.0
Requires-Dist: google-cloud-logging ==3.13.0
Requires-Dist: google-cloud-monitoring ==2.28.0
Requires-Dist: google-cloud-storage ==2.19.0
Requires-Dist: pyrate-limiter ==2.10.0
Requires-Dist: retrying ==1.4.2
